arg/__init__.py
arg/__version__.py
arg/Aggregation/__init__.py
arg/Aggregation/argAggregatorBase.py
arg/Aggregation/argExodusAggregator.py
arg/Aggregation/argVTKSTLAggregator.py
arg/Applications/ARG.py
arg/Applications/Explorator.py
arg/Applications/__init__.py
arg/Applications/argExplorator.py
arg/Applications/argGenerator.py
arg/Backend/__init__.py
arg/Backend/argBackend.py
arg/Backend/argBackendBase.py
arg/Backend/argLaTeXBackend.py
arg/Backend/argReportLaTeXBackend.py
arg/Backend/argReportWordBackend.py
arg/Backend/argWordBackend.py
arg/Common/__init__.py
arg/Common/argInformationObject.py
arg/Common/argMath.py
arg/Common/argMultiFontStringHelper.py
arg/Common/argReportParameters.py
arg/Common/argTools.py
arg/Common/argTypes.yml
arg/DataInterface/__init__.py
arg/DataInterface/argDataInterface.py
arg/DataInterface/argDataInterfaceBase.py
arg/DataInterface/argHDF5Reader.py
arg/DataInterface/argKeyValueFilesReader.py
arg/DataInterface/argVTKExodusReader.py
arg/DataInterface/argVTKSTLReader.py
arg/Generation/__init__.py
arg/Generation/argPlot.py
arg/Generation/argVTK.py
arg/Tools/Utilities.py
arg/Tools/__init__.py
pyARG-1.2.3.dist-info/LICENSE
pyARG-1.2.3.dist-info/METADATA
pyARG-1.2.3.dist-info/WHEEL
pyARG-1.2.3.dist-info/top_level.txt
pyARG-1.2.3.dist-info/RECORD
