Metadata-Version: 2.1
Name: pyARG
Version: 1.2.3
Summary: This is the official PyPi repository for ARG project.
Home-page: UNKNOWN
Author: NexGen Analytics
Author-email: info@ng-analytics.com
License: UNKNOWN
Platform: UNKNOWN
Classifier: License :: OSI Approved :: BSD License
Classifier: Programming Language :: Python :: 3
Classifier: Programming Language :: Python :: 3 :: Only
Classifier: Programming Language :: Python :: 3.7
Classifier: Programming Language :: Python :: 3.8
Classifier: Programming Language :: Python :: 3.9
Classifier: Operating System :: MacOS
Classifier: Operating System :: Microsoft :: Windows
Classifier: Operating System :: Unix
Requires-Python: >=3.7
License-File: LICENSE
Requires-Dist: pyARG-dep (==0.0.14)
